svst/__init__.py
svst/api.py
svst/cli.py
svst/config.py
svst/constants.py
svst/output.py
svst/parsing.py
svst/utils.py
svst-0.1.15.dist-info/LICENSE
svst-0.1.15.dist-info/METADATA
svst-0.1.15.dist-info/WHEEL
svst-0.1.15.dist-info/entry_points.txt
svst-0.1.15.dist-info/top_level.txt
svst-0.1.15.dist-info/RECORD
