Metadata-Version: 2.1
Name: svst
Version: 0.1.15
Summary: Standalone Variables Static Typing
Home-page: https://svst.readthedocs.io/
Author: Spiked Engineering
Author-email: spikedengineering@tutanota.com
License: MPL2
Project-URL: Code Repository, https://github.com/spikedengineering/svst
Project-URL: Documentation, https://svst.readthedocs.io/
Platform: UNKNOWN
Classifier: Intended Audience :: Developers
Classifier: License :: OSI Approved :: Mozilla Public License 2.0 (MPL 2.0)
Classifier: Programming Language :: Python
Classifier: Programming Language :: Python :: 3
Classifier: Programming Language :: Python :: 3.7
Classifier: Programming Language :: Python :: 3.8
Classifier: Programming Language :: Python :: 3.9
Classifier: Programming Language :: Python :: 3.10
Classifier: Programming Language :: Python :: 3.11
Classifier: Programming Language :: Python :: 3.12
Classifier: Operating System :: OS Independent
Requires-Dist: mypy
